pcap_inspector/__init__.py
pcap_inspector/cli.py
pcap_inspector/decode_pkts.py
pcap_inspector/file_extractor.py
pcap_inspector/pcap_stats.py
pcap_inspector/stream_reassembly.py
pcap_inspector-0.1.0.dist-info/METADATA
pcap_inspector-0.1.0.dist-info/WHEEL
pcap_inspector-0.1.0.dist-info/entry_points.txt
pcap_inspector-0.1.0.dist-info/licenses/LICENSE
pcap_inspector-0.1.0.dist-info/RECORD
