Metadata-Version: 2.4
Name: pcap-inspector
Version: 0.1.0
Summary: A Python package for analyzing pcap files to find CTF flags and extract files
Project-URL: Homepage, https://github.com/pratima-sapkota/pcap-inspector
Project-URL: Repository, https://github.com/pratima-sapkota/pcap-inspector
Project-URL: Issues, https://github.com/pratima-sapkota/pcap-inspector/issues
Author: Pratima Sapkota
License: MIT
License-File: LICENSE
Keywords: capture-the-flag,ctf,flag,forensics,network,packet-analysis,pcap,pcapng,scapy,security
Classifier: Development Status :: 4 - Beta
Classifier: Environment :: Console
Classifier: Intended Audience :: Developers
Classifier: Intended Audience :: Information Technology
Classifier: Intended Audience :: Science/Research
Classifier: License :: OSI Approved :: MIT License
Classifier: Operating System :: OS Independent
Classifier: Programming Language :: Python :: 3
Classifier: Programming Language :: Python :: 3.10
Classifier: Programming Language :: Python :: 3.11
Classifier: Programming Language :: Python :: 3.12
Classifier: Programming Language :: Python :: 3.13
Classifier: Topic :: Security
Classifier: Topic :: System :: Networking :: Monitoring
Classifier: Typing :: Typed
Requires-Python: >=3.10
Requires-Dist: scapy>=2.6.1
Provides-Extra: dev
Requires-Dist: mypy>=1.0.0; extra == 'dev'
Requires-Dist: pytest>=8.0.0; extra == 'dev'
